frauddetector/__init__.py
frauddetector/frauddetector.py
frauddetector/metrics.py
frauddetector/profiler.py
frauddetector-0.2.0.dist-info/LICENSE
frauddetector-0.2.0.dist-info/METADATA
frauddetector-0.2.0.dist-info/NOTICE
frauddetector-0.2.0.dist-info/WHEEL
frauddetector-0.2.0.dist-info/top_level.txt
frauddetector-0.2.0.dist-info/zip-safe
frauddetector-0.2.0.dist-info/RECORD
