Metadata-Version: 2.1
Name: frauddetector
Version: 0.2.0
Summary: Python SDK for Amazon Fraud Detector
Home-page: 
Author: Edward Bullen, Oliver Zollikofer, Michael Wallner
Author-email: bullee@amazon.com, zolliko@amazon.ch, wallnm@amazon.com
License: Apache-2.0
Platform: UNKNOWN
License-File: LICENSE
License-File: NOTICE
Requires-Dist: numpy
Requires-Dist: pandas
Requires-Dist: boto3
Requires-Dist: scikit-image
Requires-Dist: seaborn
Requires-Dist: matplotlib
Requires-Dist: ipython
